emoji-list/__init__.py
emoji_list/__init__.py
emoji_list-0.50.dist-info/DESCRIPTION.rst
emoji_list-0.50.dist-info/METADATA
emoji_list-0.50.dist-info/RECORD
emoji_list-0.50.dist-info/WHEEL
emoji_list-0.50.dist-info/metadata.json
emoji_list-0.50.dist-info/top_level.txt
