Metadata-Version: 2.0
Name: emoji-list
Version: 0.50
Summary: Raw lists of emoji by type, stripped so you don't have to
Home-page: http://github.com/vincentmwong/emoji_list
Author: Vincent Wong
Author-email: vmwong1@gmail.com
License: MIT
Keywords: emoji
Platform: UNKNOWN
